mcp_voice_salute/__init__.py
mcp_voice_salute/__main__.py
mcp_voice_salute/server.py
mcp_voice_salute-0.1.2.dist-info/METADATA
mcp_voice_salute-0.1.2.dist-info/WHEEL
mcp_voice_salute-0.1.2.dist-info/entry_points.txt
mcp_voice_salute-0.1.2.dist-info/top_level.txt
mcp_voice_salute-0.1.2.dist-info/RECORD
