Metadata-Version: 2.4
Name: mcp_voice_salute
Version: 0.1.2
Summary: MCP сервер для работы с голосовыми API SaluteSpeech от Сбера
Author-email: Sergei Trashchenkov <trashchenkov@gmail.com>
License: MIT
Project-URL: Homepage, https://github.com/trashchenkov/mcp_voice_salute
Requires-Python: >=3.12
Requires-Dist: httpx>=0.28.1
Requires-Dist: mcp[cli]>=1.6.0
Requires-Dist: pyaudio>=0.2.14
Requires-Dist: speechrecognition>=3.14.2
Requires-Dist: sounddevice>=0.5.1
Requires-Dist: numpy>=1.26.0
Requires-Dist: uv>=0.7.2
